Metadata-Version: 1.0
Name: django-user-roles
Version: 0.1.0
Summary: Simple role-based user permissions for Django.
Home-page: http://github.com/dabapps/django-user-roles
Author: Tom Christie
Author-email: tom@tomchristie.com
License: BSD
Platform: UNKNOWN
